mcp_stock_jk/__init__.py
mcp_stock_jk/__main__.py
mcp_stock_jk/server.py
mcp_stock_jk-0.0.1.dist-info/METADATA
mcp_stock_jk-0.0.1.dist-info/WHEEL
mcp_stock_jk-0.0.1.dist-info/entry_points.txt
mcp_stock_jk-0.0.1.dist-info/RECORD
