Metadata-Version: 2.4
Name: mcp_stock_jk
Version: 0.0.1
Summary: MCP Server for Stock prices
Requires-Python: >=3.11
Requires-Dist: fastmcp
Requires-Dist: mcp[cli]>=1.2.0
Requires-Dist: requests>=2.32.3
Requires-Dist: yfinance
